pyscaffoldext/markdown/__init__.py
pyscaffoldext/markdown/extension.py
pyscaffoldext/markdown/templates/__init__.py
pyscaffoldext/markdown/templates/authors.template
pyscaffoldext/markdown/templates/changelog.template
pyscaffoldext/markdown/templates/contributing.template
pyscaffoldext/markdown/templates/index.template
pyscaffoldext/markdown/templates/license.template
pyscaffoldext/markdown/templates/myst_extensions.template
pyscaffoldext/markdown/templates/readme.template
pyscaffoldext_markdown-0.5.dist-info/AUTHORS.md
pyscaffoldext_markdown-0.5.dist-info/LICENSE.txt
pyscaffoldext_markdown-0.5.dist-info/METADATA
pyscaffoldext_markdown-0.5.dist-info/WHEEL
pyscaffoldext_markdown-0.5.dist-info/entry_points.txt
pyscaffoldext_markdown-0.5.dist-info/top_level.txt
pyscaffoldext_markdown-0.5.dist-info/RECORD
