Metadata-Version: 2.1
Name: pyscaffoldext-markdown
Version: 0.5
Summary: PyScaffold extension which uses Markdown instead of reStructuredText
Home-page: https://github.com/pyscaffold/pyscaffoldext-markdown
Author: Florian Wilhelm
Author-email: florian.wilhelm@inovex.de
License: MIT
Project-URL: Documentation, https://pyscaffold.org/
Project-URL: Source, https://github.com/pyscaffold/pyscaffoldext-markdown/
Project-URL: Tracker, https://github.com/pyscaffold/pyscaffoldext-markdown/
Project-URL: Changelog, https://pyscaffold.org/projects/markdown/en/latest/changelog.html
Project-URL: Conda-Forge, https://anaconda.org/conda-forge/pyscaffoldext-markdown
Project-URL: Download, https://pypi.org/project/pyscaffoldext-markdown/#files
Project-URL: Twitter, https://twitter.com/PyScaffold
Platform: any
Classifier: Development Status :: 4 - Beta
Classifier: Topic :: Utilities
Classifier: Programming Language :: Python
Classifier: Programming Language :: Python :: 3
Classifier: Programming Language :: Python :: 3 :: Only
Classifier: Environment :: Console
Classifier: Intended Audience :: Developers
Classifier: License :: OSI Approved :: MIT License
Classifier: Operating System :: POSIX :: Linux
Classifier: Operating System :: Unix
Classifier: Operating System :: MacOS
Classifier: Operating System :: Microsoft :: Windows
Requires-Python: >=3.6
License-File: LICENSE.txt
License-File: AUTHORS.md
Requires-Dist: pyscaffold (<5.0a0,>=4.1rc1)
Requires-Dist: wheel (>=0.31)
Requires-Dist: myst-parser[linkify]
Requires-Dist: importlib-metadata ; python_version < "3.8"
Provides-Extra: testing
Requires-Dist: tox ; extra == 'testing'
Requires-Dist: pre-commit ; extra == 'testing'
Requires-Dist: setuptools-scm ; extra == 'testing'
Requires-Dist: virtualenv ; extra == 'testing'
Requires-Dist: twine ; extra == 'testing'
Requires-Dist: configupdater ; extra == 'testing'
Requires-Dist: pytest ; extra == 'testing'
Requires-Dist: pytest-cov ; extra == 'testing'
Requires-Dist: pytest-xdist ; extra == 'testing'
